jaseci_serv/VERSION
jaseci_serv/__init__.py
jaseci_serv/asgi.py
jaseci_serv/settings.py
jaseci_serv/urls.py
jaseci_serv/wsgi.py
jaseci_serv/base/__init__.py
jaseci_serv/base/admin.py
jaseci_serv/base/apps.py
jaseci_serv/base/jsorc.py
jaseci_serv/base/jsorc_loadtest.py
jaseci_serv/base/models.py
jaseci_serv/base/example_jac/__init__.py
jaseci_serv/base/example_jac/discussion_analysis.jac
jaseci_serv/base/example_jac/flight_chatbot.jac
jaseci_serv/base/example_jac/flow_analysis.jac
jaseci_serv/base/example_jac/restaurant_chatbot.jac
jaseci_serv/base/example_jac/sentence_pairing.jac
jaseci_serv/base/example_jac/virtual_assistant.jac
jaseci_serv/base/example_jac/zeroshot_faq_bot.jac
jaseci_serv/base/management/__init__.py
jaseci_serv/base/management/commands/__init__.py
jaseci_serv/base/management/commands/createdb.py
jaseci_serv/base/management/commands/dropdb.py
jaseci_serv/base/management/commands/wait_for_db.py
jaseci_serv/base/tests/__init__.py
jaseci_serv/base/tests/aitest_ai_models.py
jaseci_serv/base/tests/mock_redis.py
jaseci_serv/base/tests/test_admin.py
jaseci_serv/base/tests/test_commands.py
jaseci_serv/base/tests/test_models.py
jaseci_serv/base/tests/test_orm_hooks.py
jaseci_serv/base/tests/test_orm_hooks_cfg.py
jaseci_serv/hook/__init__.py
jaseci_serv/hook/orm.py
jaseci_serv/jac_api/__init__.py
jaseci_serv/jac_api/api.py
jaseci_serv/jac_api/apps.py
jaseci_serv/jac_api/urls.py
jaseci_serv/jac_api/views.py
jaseci_serv/jac_api/tests/__init__.py
jaseci_serv/jac_api/tests/async_update.jac
jaseci_serv/jac_api/tests/general.jac
jaseci_serv/jac_api/tests/infer.py
jaseci_serv/jac_api/tests/ll.jac
jaseci_serv/jac_api/tests/ll_wall.jac
jaseci_serv/jac_api/tests/object_bug.jac
jaseci_serv/jac_api/tests/public.jac
jaseci_serv/jac_api/tests/public_updated.jac
jaseci_serv/jac_api/tests/test_jac_admin_api.py
jaseci_serv/jac_api/tests/test_jac_api.py
jaseci_serv/jac_api/tests/test_jac_general.py
jaseci_serv/jac_api/tests/test_ll.py
jaseci_serv-1.4.2.6.dist-info/LICENSE
jaseci_serv-1.4.2.6.dist-info/METADATA
jaseci_serv-1.4.2.6.dist-info/WHEEL
jaseci_serv-1.4.2.6.dist-info/top_level.txt
jaseci_serv-1.4.2.6.dist-info/RECORD
