Metadata-Version: 2.1
Name: jaseci_serv
Version: 1.4.2.6
Home-page: https://github.com/Jaseci-Labs/jaseci
Author: Jason Mars
Author-email: jason@jaseci.org
License-File: LICENSE
Requires-Dist: jaseci
Requires-Dist: Django<3.3.0,>=3.2.12
Requires-Dist: djangorestframework<3.14.0,>=3.13.1
Requires-Dist: django-rest-knox<4.3.0,>=4.2.0
Requires-Dist: django-rest-passwordreset<1.3.0,>=1.2.1
Requires-Dist: drf-yasg<1.21.0,>=1.20.0
Requires-Dist: markdown<3.4.0,>=3.3.6
Requires-Dist: psycopg2-binary<3,>=2
Requires-Dist: sphinx<2.5.0,>=2.4.3
Requires-Dist: django-cors-headers
Requires-Dist: tblib
Requires-Dist: django-celery-results<2.4,>=2.3
Requires-Dist: django-celery-beat>=2.2
Requires-Dist: pytest-django
Requires-Dist: dj-rest-auth[with_social]==4.0.1
Requires-Dist: tzdata>=2022.7
